fair_lnc_evaluation/__init__.py
fair_lnc_evaluation/classifier.py
fair_lnc_evaluation/data.py
fair_lnc_evaluation/empirical_evaluation.py
fair_lnc_evaluation/metrics.py
fair_lnc_evaluation/noise_injection.py
fair_lnc_evaluation-0.0.1.dist-info/METADATA
fair_lnc_evaluation-0.0.1.dist-info/WHEEL
fair_lnc_evaluation-0.0.1.dist-info/licenses/LICENSE
fair_lnc_evaluation-0.0.1.dist-info/RECORD
