Metadata-Version: 2.1
Name: fair_lnc_evaluation
Version: 0.0.1
Summary: Methodology for the systematic evaluation of label noise correction methods for ML fairness.
Project-URL: Homepage, https://github.com/reluzita/fair-lnc-evaluation
Author-email: Inês Silva <inesoliveiraesilva@gmail.com>
License-File: LICENSE
Classifier: License :: OSI Approved :: MIT License
Classifier: Operating System :: OS Independent
Classifier: Programming Language :: Python :: 3
Requires-Python: >=3.7
